[
  {
    "version": "27.05.2026",
    "description": "- Đồng bộ phiên bản trên các giao diện khác nhau\n- Sửa giao diện trang cài đặt\n- Sửa giao diện Widget\n- Sửa lỗi hiển thị lịch sử báo cáo khi ấn vào thông báo\n- Thêm chức năng sửa tên danh mục (Thu - Chi)\n- Pdf báo cáo theo năm đẹp mắt",
    "order": 13
  },
  {
    "version": "26.05.2026",
    "description": "- Chỉnh sửa giao diện trang lịch sử mua - bán - đổi vàng\n- Mặc định ẩn tiền lúc đầu\n- Sửa điều kiện đổi vàng\n- Thay đổi cơ chế mã hóa dữ liệu\n- Thêm Widget",
    "order": 12
  },
  {
    "version": "25.05.2026",
    "description": "- Sửa lỗi sao lưu tự động\n- Sửa giao diện hiển thị\n- Sửa lỗi ấn vào thông báo hằng ngày\n- Thêm chức năng sửa chú thích giao dịch\n- Thêm chức năng hiển thị gợi ý ghi chú\n- Hiển thị bản sao lưu mới nhất khi ấn khôi phục\n- Cập nhật xóa bản sao lưu cũ khi sao lưu đạt tối đa 20 bản\n- Sửa giao diện trang cài đặt\n- Thêm trang lưu lịch sử mua - bán - đổi vàng",
    "order": 11
  },
  {
    "version": "23.05.2026",
    "description": "- Sửa phần hiển thị tên ở các trang khác\n- Sửa hiển thị báo cáo tài chính\n- Sửa trang hướng dẫn sinh động hơn\n- Thu nhỏ icon ẩn tiền\n- Hiển thị lọc theo điều kiện nào ở biểu đồ tròn",
    "order": 10
  },
  {
    "version": "22.05.2026",
    "description": "- Cập nhật sao lưu dữ liệu ở trang bắt đầu\n- Thay đổi cơ chế linh vật\n- Bổ sung hướng dẫn chi tiết\n- Lời chào trang chủ chi tiết hơn\n- Sửa lỗi hiển thị tên người dùng\n- Tối ưu giao diện hiển thị tiền\n- Sửa lỗi sao lưu dữ liệu\n- Sửa lỗi hiển thị bản sao lưu mới nhất",
    "order": 9
  },
  {
    "version": "21.05.2026",
    "description": "- Sửa giao diện profile\n- Mã hóa dữ liệu\n- Thêm linh vật giữ chuỗi",
    "order": 8
  },
  {
    "version": "20.05.2026",
    "description": "- Thêm chức năng giữ chuỗi\n- Backup dữ liệu tự động\n- Thông báo thu chi theo ngày, tháng, năm",
    "order": 7
  },
  {
    "version": "14.05.2026",
    "description": "- Thêm icon sinh động cho danh mục, Quỹ",
    "order": 6
  },
  {
    "version": "10.05.2026",
    "description": "- Thêm Quỹ lưu trữ",
    "order": 5
  },
  {
    "version": "01.05.2026",
    "description": "- Sửa lỗi logic xóa giao dịch",
    "order": 4
  },
  {
    "version": "21.04.2026",
    "description": "- Sửa, xóa giao dịch trong vòng 3 ngày",
    "order": 3
  },
  {
    "version": "15.04.2026",
    "description": "- Chia 2 loại danh mục chi tiền: \n1. Cần nạp tiền\n2. Chi trực tiếp",
    "order": 2
  },
  {
    "version": "15.03.2026",
    "description": "- Ra mắt ứng dụng lúc 23:36",
    "order": 1
  }
]